LatDi/__init__.py
LatDi/complexdimensionalityreduction.py
LatDi-0.0.4.dist-info/LICENSE
LatDi-0.0.4.dist-info/METADATA
LatDi-0.0.4.dist-info/WHEEL
LatDi-0.0.4.dist-info/top_level.txt
LatDi-0.0.4.dist-info/RECORD
