Metadata-Version: 2.1
Name: LatDi
Version: 0.0.4
Summary: Lateral Dimensionality Reduction
Author: SussyMongoosey (Jack Martin)
Author-email: <johnelliotmartin@gmail.com>
Keywords: python,pandas,numpy,feature engineering,dimensionality reduction
Classifier: Development Status :: 1 - Planning
Classifier: Intended Audience :: Developers
Classifier: Programming Language :: Python :: 3
Classifier: Operating System :: Unix
Classifier: Operating System :: MacOS :: MacOS X
Classifier: Operating System :: Microsoft :: Windows
License-File: LICENSE
Requires-Dist: pandas
Requires-Dist: numpy
